[{"id":0,"title":"Samsung S20","description":"Celular smartphone 20","code":500,"price":200,"status":true,"stock":15,"category":"Celular","thumbnail":[]},{"id":4,"title":"Samsung S20","description":"Celular smartphone 20","code":504,"price":200,"status":true,"stock":15,"category":"Celular","thumbnail":[]},{"id":5,"title":"Samsung S20","description":"Celular smartphone 20","code":505,"price":200,"status":true,"stock":15,"category":"Celular","thumbnail":[]},{"id":6,"title":"Samsung S20","description":"Celular smartphone 20","code":506,"price":200,"status":true,"stock":15,"category":"Celular","thumbnail":[]},{"id":7,"title":"Samsung S20","description":"Celular smartphone 20","code":507,"price":200,"status":true,"stock":15,"category":"Celular","thumbnail":[]},{"id":8,"title":"Samsung S20","description":"Celular smartphone 20","code":508,"price":200,"status":true,"stock":15,"category":"Celular","thumbnail":[]},{"id":9,"title":"Samsung S20","description":"Celular smartphone 20","code":509,"price":200,"status":true,"stock":15,"category":"Celular","thumbnail":[]},{"id":10,"title":"Samsung S20","description":"Celular smartphone 20","code":510,"price":200,"status":true,"stock":15,"category":"Celular","thumbnail":[]},{"id":11,"status":true,"title":"Samsung S20","description":"Celular smartphone 20","code":511,"price":200,"stock":15,"category":"Celular","thumbnail":[]},{"id":13,"status":true,"title":"Samsung S20","description":"Celular smartphone 20","code":511,"price":200,"stock":15,"category":"Celular","thumbnail":[]},{"id":14,"status":true,"title":"Samsung S20","description":"Celular smartphone 20","code":513,"price":200,"stock":15,"category":"Celular","thumbnail":[]},{"id":15,"status":true,"title":"Samsung S20","description":"Celular smartphone 20","code":513,"price":200,"stock":15,"category":"Celular","thumbnail":[]},{"id":16,"status":true,"title":"Samsung S20","description":"Celular smartphone 20","code":514,"price":200,"stock":15,"category":"Celular","thumbnail":[]}]